radosgw/__init__.py
radosgw/bucket.py
radosgw/connection.py
radosgw/exception.py
radosgw/user.py
radosgw/utils.py
radosgw_admin-1.7.2.dist-info/LICENSE
radosgw_admin-1.7.2.dist-info/METADATA
radosgw_admin-1.7.2.dist-info/WHEEL
radosgw_admin-1.7.2.dist-info/top_level.txt
radosgw_admin-1.7.2.dist-info/RECORD
