Metadata-Version: 2.1
Name: radosgw-admin
Version: 1.7.2
Summary: Ceph RADOS Gateway (rgw) admin operations REST API
Home-page: https://github.com/valerytschopp/python-radosgw-admin
Author: Valery Tschopp
Author-email: valery.tschopp@gmail.com
License: GPLv3
Platform: UNKNOWN
Requires: boto
Requires-Dist: boto
